Metadata-Version: 2.1
Name: odoo14-addon-hr-timesheet-sheet-period
Version: 14.0.1.0.1.dev11
Summary: HR Timesheet Sheet based on Payroll Period
Home-page: https://github.com/OCA/timesheet
Author: ForgeFlow S.L., Serpent Consulting Services Pvt. Ltd., Odoo Community Association (OCA)
Author-email: support@odoo-community.org
License: AGPL-3
Platform: UNKNOWN
Classifier: Programming Language :: Python
Classifier: Framework :: Odoo
Classifier: Framework :: Odoo :: 14.0
Classifier: License :: OSI Approved :: GNU Affero General Public License v3
Requires-Python: >=3.6
Requires-Dist: odoo14-addon-hr-period
Requires-Dist: odoo14-addon-hr-timesheet-sheet
Requires-Dist: odoo <14.1dev,>=14.0a
